<annotation>
	<folder>Pakistan CNIC</folder>
	<filename>2.png</filename>
	<path>E:\Monisa Semester 7\Data Science\Assignments\Project\Pakistan CNIC\2.png</path>
	<source>
		<database>Unknown</database>
	</source>
	<size>
		<width>685</width>
		<height>457</height>
		<depth>3</depth>
	</size>
	<segmented>0</segmented>
	<object>
		<name>Country</name>
		<pose>Unspecified</pose>
		<truncated>0</truncated>
		<difficult>0</difficult>
		<bndbox>
			<xmin>194</xmin>
			<ymin>36</ymin>
			<xmax>350</xmax>
			<ymax>71</ymax>
		</bndbox>
	</object>
	<object>
		<name>Name</name>
		<pose>Unspecified</pose>
		<truncated>0</truncated>
		<difficult>0</difficult>
		<bndbox>
			<xmin>232</xmin>
			<ymin>107</ymin>
			<xmax>339</xmax>
			<ymax>129</ymax>
		</bndbox>
	</object>
	<object>
		<name>Identity Card No</name>
		<pose>Unspecified</pose>
		<truncated>0</truncated>
		<difficult>0</difficult>
		<bndbox>
			<xmin>223</xmin>
			<ymin>319</ymin>
			<xmax>359</xmax>
			<ymax>344</ymax>
		</bndbox>
	</object>
	<object>
		<name>Date of Birth</name>
		<pose>Unspecified</pose>
		<truncated>0</truncated>
		<difficult>0</difficult>
		<bndbox>
			<xmin>376</xmin>
			<ymin>322</ymin>
			<xmax>460</xmax>
			<ymax>346</ymax>
		</bndbox>
	</object>
	<object>
		<name>Date of Expiry</name>
		<pose>Unspecified</pose>
		<truncated>0</truncated>
		<difficult>0</difficult>
		<bndbox>
			<xmin>377</xmin>
			<ymin>369</ymin>
			<xmax>465</xmax>
			<ymax>393</ymax>
		</bndbox>
	</object>
</annotation>
